ov/__init__.py
ov-0.0.4.dist-info/LICENSE
ov-0.0.4.dist-info/METADATA
ov-0.0.4.dist-info/WHEEL
ov-0.0.4.dist-info/top_level.txt
ov-0.0.4.dist-info/RECORD
